pyfunvice/__init__.py
pyfunvice/cli.py
pyfunvice/common_func.py
pyfunvice/docker_cli.py
pyfunvice/struct.py
pyfunvice-0.1.12.dist-info/METADATA
pyfunvice-0.1.12.dist-info/WHEEL
pyfunvice-0.1.12.dist-info/entry_points.txt
pyfunvice-0.1.12.dist-info/RECORD
